Workbook

Sheet Contexte Danone
A1: Danone – Analyse des risques achats (MS Achats)
A2: Matrice de dépendance · Matrice de risques · Matrice prospective (5 ans) · Recommandations
A4: Entreprise | B4: Danone SA – groupe agroalimentaire français (siège : Paris), présent dans plus de 120 pays.
A5: Métiers | B5: 1) Produits laitiers et d'origine végétale (Danone, Activia, Actimel, Alpro, Oikos, Danio…) 2) Eaux (Evian, Volvic, Badoit, Aqua…) 3) Nutrition spécialisée (lait infantile Blédina / Aptamil / Gallia, nutrition médicale Nutricia).
A6: Achats stratégiques | B6: • Lait cru (collecte auprès de milliers d'éleveurs) et ingrédients laitiers (poudres, protéines) • Matières végétales : soja, avoine, amandes, fruits, sucre, cacao • Emballages : PET / rPET (bouteilles d'eau), pots plastique et carton • Énergie (sites industriels, chaîne du froid) et transport • Accès à la ressource en eau (impluviums d'Evian et Volvic)
A7: Spécificités risques | B7: Produits frais à DLC courte (chaîne logistique tendue), exigences sanitaires maximales sur la nutrition infantile, forte exposition aux sujets climat / eau / plastique (image de marque), dépendance au modèle d'élevage laitier.
A8: Méthode | B8: 1. Matrice de dépendance : les variables en ligne influencent les variables en colonne (x). 2. Plan influence / dépendance : classement des variables (motrices, relais, dépendantes, autonomes). 3. Matrice de risques : fréquence × impact (échelle 1 à 5). 4. Matrice prospective : 5 hypothèses à 5 ans par variable clé, puis scénarios narratifs. 5. Recommandations stratégiques.
A9: Légende | B9: Cellules jaunes = variables clés retenues · Cellules 'x' et notes de fréquence/impact = hypothèses de travail modifiables (les totaux, scores et graphiques se recalculent).
A10: Avertissement | B10: Les notations et hypothèses chiffrées sont des estimations pédagogiques du groupe, pas des données publiées par Danone.

Sheet Matrice de dépendance
A1: Matrice de dépendance – Danone
A2: Lecture : la variable en LIGNE influence la variable en COLONNE (x). Total 1 = influence (motricité), Total 2 = dépendance.
A4: Variables | B4: Prix du lait | C4: Prix MP agricoles | D4: Énergie / carburants | E4: Emballages | F4: Réchauffement climatique | G4: Ressource en eau | H4: Régl. sanitaires | I4: Régl. environnementales | J4: Fiabilité fournisseurs | K4: Stabilité géopolitique | L4: Fiabilité logistique | M4: Tarifs douaniers | N4: Sanctions / compliance | O4: Épizooties | P4: Tendances de conso | Q4: Pression distribution | R4: Climat social | S4: Cours mondiaux | T4: TOTAL 1 Influence | U4: TOTAL 2 Dépendance | V4: TOTAL 1+2
A5: Prix du lait cru (collecte laitière) | J5: x | Q5: x | R5: x | S5: x | T5: =COUNTA(B5:S5) -> 4 | U5: =COUNTA(B5:B22) -> 10 | V5: =SUM(T5:U5) -> 14
A6: Prix des matières premières agricoles (sucre, fruits, soja, avoine, amandes) | Q6: x | S6: x | T6: =COUNTA(B6:S6) -> 2 | U6: =COUNTA(C5:C22) -> 7 | V6: =SUM(T6:U6) -> 9
A7: Prix de l'énergie / carburants | B7: x | C7: x | E7: x | L7: x | R7: x | S7: x | T7: =COUNTA(B7:S7) -> 6 | U7: =COUNTA(D5:D22) -> 4 | V7: =SUM(T7:U7) -> 10
A8: Prix et disponibilité des emballages (PET, rPET, carton) | Q8: x | T8: =COUNTA(B8:S8) -> 1 | U8: =COUNTA(E5:E22) -> 4 | V8: =SUM(T8:U8) -> 5
A9: Réchauffement climatique / sécheresses | B9: x | C9: x | G9: x | I9: x | J9: x | K9: x | L9: x | O9: x | P9: x | S9: x | T9: =COUNTA(B9:S9) -> 10 | U9: =COUNTA(F5:F22) -> 0 | V9: =SUM(T9:U9) -> 10
A10: Ressource en eau (sources minérales, nappes) | I10: x | P10: x | T10: =COUNTA(B10:S10) -> 2 | U10: =COUNTA(G5:G22) -> 1 | V10: =SUM(T10:U10) -> 3
A11: Réglementations sanitaires / nutritionnelles | B11: x | J11: x | M11: x | P11: x | Q11: x | T11: =COUNTA(B11:S11) -> 5 | U11: =COUNTA(H5:H22) -> 2 | V11: =SUM(T11:U11) -> 7
A12: Réglementations environnementales (emballages, méthane, CSRD) | B12: x | D12: x | E12: x | J12: x | P12: x | Q12: x | R12: x | T12: =COUNTA(B12:S12) -> 7 | U12: =COUNTA(I5:I22) -> 3 | V12: =SUM(T12:U12) -> 10
A13: Fiabilité des fournisseurs / renouvellement des éleveurs | B13: x | R13: x | S13: x | T13: =COUNTA(B13:S13) -> 3 | U13: =COUNTA(J5:J22) -> 8 | V13: =SUM(T13:U13) -> 11
A14: Stabilité géopolitique des zones de production | C14: x | D14: x | L14: x | M14: x | N14: x | S14: x | T14: =COUNTA(B14:S14) -> 6 | U14: =COUNTA(K5:K22) -> 3 | V14: =SUM(T14:U14) -> 9
A15: Fiabilité logistique / routes maritimes | C15: x | D15: x | E15: x | S15: x | T15: =COUNTA(B15:S15) -> 4 | U15: =COUNTA(L5:L22) -> 5 | V15: =SUM(T15:U15) -> 9
A16: Tarifs douaniers / protectionnisme | C16: x | E16: x | K16: x | Q16: x | S16: x | T16: =COUNTA(B16:S16) -> 5 | U16: =COUNTA(M5:M22) -> 4 | V16: =SUM(T16:U16) -> 9
A17: Sanctions internationales / compliance | D17: x | K17: x | L17: x | M17: x | T17: =COUNTA(B17:S17) -> 4 | U17: =COUNTA(N5:N22) -> 1 | V17: =SUM(T17:U17) -> 5
A18: Épizooties (FCO, fièvre aphteuse, grippe aviaire) | B18: x | H18: x | J18: x | M18: x | R18: x | S18: x | T18: =COUNTA(B18:S18) -> 6 | U18: =COUNTA(O5:O22) -> 1 | V18: =SUM(T18:U18) -> 7
A19: Tendances de consommation / opinion (végétal, santé, boycotts) | B19: x | C19: x | I19: x | Q19: x | T19: =COUNTA(B19:S19) -> 4 | U19: =COUNTA(P5:P22) -> 4 | V19: =SUM(T19:U19) -> 8
A20: Pression de la distribution & concurrence (MDD, Egalim) | B20: x | J20: x | R20: x | T20: =COUNTA(B20:S20) -> 3 | U20: =COUNTA(Q5:Q22) -> 8 | V20: =SUM(T20:U20) -> 11
A21: Climat social (agricole et industriel) | B21: x | H21: x | J21: x | L21: x | T21: =COUNTA(B21:S21) -> 4 | U21: =COUNTA(R5:R22) -> 6 | V21: =SUM(T21:U21) -> 10
A22: Cours mondiaux / spéculation (poudre de lait, beurre, sucre) | B22: x | C22: x | J22: x | Q22: x | T22: =COUNTA(B22:S22) -> 4 | U22: =COUNTA(S5:S22) -> 9 | V22: =SUM(T22:U22) -> 13
A23: TOTAL 2 (dépendance) | B23: =COUNTA(B5:B22) -> 10 | C23: =COUNTA(C5:C22) -> 7 | D23: =COUNTA(D5:D22) -> 4 | E23: =COUNTA(E5:E22) -> 4 | F23: =COUNTA(F5:F22) -> 0 | G23: =COUNTA(G5:G22) -> 1 | H23: =COUNTA(H5:H22) -> 2 | I23: =COUNTA(I5:I22) -> 3 | ... S23: =COUNTA(S5:S22) -> 9
A25: Contrôle : somme des influences = somme des dépendances | B25: =IF(SUM(T5:T22)=SUM(B23:S23),"OK","Écart") -> OK

Sheet Influence-Dépendance
A1: Plan influence / dépendance (type MICMAC)
A2: Calculé automatiquement depuis la matrice de dépendance. Seuils = moyennes.
A4: Variable | B4: Influence | C4: Dépendance | D4: Classe
A5: Prix du lait | B5: ='Matrice de dépendance'!T5 -> 4 | C5: ='Matrice de dépendance'!U5 -> 10 | D5: =IF(AND(B5>=$B$25,C5<$C$25),"Motrice (entrée)",IF(AND(B5>=$B$25,C5>=$C$25),"Relais (enjeu)",IF(C5>=$C$25,"Dépendante (résultat)","Autonome"))) -> Dépendante (résultat)
A6: Prix MP agricoles | B6: ='Matrice de dépendance'!T6 -> 2 | C6: ='Matrice de dépendance'!U6 -> 7 | D6: =IF(AND(B6>=$B$25,C6<$C$25),"Motrice (entrée)",IF(AND(B6>=$B$25,C6>=$C$25),"Relais (enjeu)",IF(C6>=$C$25,"Dépendante (résultat)","Autonome"))) -> Dépendante (résultat)
A7: Énergie / carburants | B7: ='Matrice de dépendance'!T7 -> 6 | C7: ='Matrice de dépendance'!U7 -> 4 | D7: =IF(AND(B7>=$B$25,C7<$C$25),"Motrice (entrée)",IF(AND(B7>=$B$25,C7>=$C$25),"Relais (enjeu)",IF(C7>=$C$25,"Dépendante (résultat)","Autonome"))) -> Motrice (entrée)
A8: Emballages | B8: ='Matrice de dépendance'!T8 -> 1 | C8: ='Matrice de dépendance'!U8 -> 4 | D8: =IF(AND(B8>=$B$25,C8<$C$25),"Motrice (entrée)",IF(AND(B8>=$B$25,C8>=$C$25),"Relais (enjeu)",IF(C8>=$C$25,"Dépendante (résultat)","Autonome"))) -> Autonome
A9: Réchauffement climatique | B9: ='Matrice de dépendance'!T9 -> 10 | C9: ='Matrice de dépendance'!U9 -> 0 | D9: =IF(AND(B9>=$B$25,C9<$C$25),"Motrice (entrée)",IF(AND(B9>=$B$25,C9>=$C$25),"Relais (enjeu)",IF(C9>=$C$25,"Dépendante (résultat)","Autonome"))) -> Motrice (entrée)
A10: Ressource en eau | B10: ='Matrice de dépendance'!T10 -> 2 | C10: ='Matrice de dépendance'!U10 -> 1 | D10: =IF(AND(B10>=$B$25,C10<$C$25),"Motrice (entrée)",IF(AND(B10>=$B$25,C10>=$C$25),"Relais (enjeu)",IF(C10>=$C$25,"Dépendante (résultat)","Autonome"))) -> Autonome
A11: Régl. sanitaires | B11: ='Matrice de dépendance'!T11 -> 5 | C11: ='Matrice de dépendance'!U11 -> 2 | D11: =IF(AND(B11>=$B$25,C11<$C$25),"Motrice (entrée)",IF(AND(B11>=$B$25,C11>=$C$25),"Relais (enjeu)",IF(C11>=$C$25,"Dépendante (résultat)","Autonome"))) -> Motrice (entrée)
A12: Régl. environnementales | B12: ='Matrice de dépendance'!T12 -> 7 | C12: ='Matrice de dépendance'!U12 -> 3 | D12: =IF(AND(B12>=$B$25,C12<$C$25),"Motrice (entrée)",IF(AND(B12>=$B$25,C12>=$C$25),"Relais (enjeu)",IF(C12>=$C$25,"Dépendante (résultat)","Autonome"))) -> Motrice (entrée)
A13: Fiabilité fournisseurs | B13: ='Matrice de dépendance'!T13 -> 3 | C13: ='Matrice de dépendance'!U13 -> 8 | D13: =IF(AND(B13>=$B$25,C13<$C$25),"Motrice (entrée)",IF(AND(B13>=$B$25,C13>=$C$25),"Relais (enjeu)",IF(C13>=$C$25,"Dépendante (résultat)","Autonome"))) -> Dépendante (résultat)
A14: Stabilité géopolitique | B14: ='Matrice de dépendance'!T14 -> 6 | C14: ='Matrice de dépendance'!U14 -> 3 | D14: =IF(AND(B14>=$B$25,C14<$C$25),"Motrice (entrée)",IF(AND(B14>=$B$25,C14>=$C$25),"Relais (enjeu)",IF(C14>=$C$25,"Dépendante (résultat)","Autonome"))) -> Motrice (entrée)
A15: Fiabilité logistique | B15: ='Matrice de dépendance'!T15 -> 4 | C15: ='Matrice de dépendance'!U15 -> 5 | D15: =IF(AND(B15>=$B$25,C15<$C$25),"Motrice (entrée)",IF(AND(B15>=$B$25,C15>=$C$25),"Relais (enjeu)",IF(C15>=$C$25,"Dépendante (résultat)","Autonome"))) -> Dépendante (résultat)
A16: Tarifs douaniers | B16: ='Matrice de dépendance'!T16 -> 5 | C16: ='Matrice de dépendance'!U16 -> 4 | D16: =IF(AND(B16>=$B$25,C16<$C$25),"Motrice (entrée)",IF(AND(B16>=$B$25,C16>=$C$25),"Relais (enjeu)",IF(C16>=$C$25,"Dépendante (résultat)","Autonome"))) -> Motrice (entrée)
... A22: Cours mondiaux | B22: ='Matrice de dépendance'!T22 -> 4 | C22: ='Matrice de dépendance'!U22 -> 9 | D22: =IF(AND(B22>=$B$25,C22<$C$25),"Motrice (entrée)",IF(AND(B22>=$B$25,C22>=$C$25),"Relais (enjeu)",IF(C22>=$C$25,"Dépendante (résultat)","Autonome"))) -> Dépendante (résultat)
A25: Moyenne (seuil) | B25: =AVERAGE(B5:B22) -> 4.4444444 | C25: =AVERAGE(C5:C22) -> 4.4444444
A27: Motrice (entrée) | B27: Variables qui conditionnent le système, peu influencées : à surveiller en veille (signaux faibles).
A28: Relais (enjeu) | B28: Très influentes ET très dépendantes : instables, leviers d'action prioritaires.
A29: Dépendante (résultat) | B29: Subissent le système : indicateurs de résultat (coûts, prix d'achat).
A30: Autonome | B30: Peu liées au reste : traitement secondaire.

Sheet Matrice de risques
A1: Matrice de risques – Danone
A2: Fréquence (probabilité) et impact notés de 1 à 5 (saisie en bleu). Score = fréquence × impact.
I3: Grille fréquence × impact (score)
A4: Variable | B4: Fréquence | C4: Impact | D4: Score | E4: Rang | F4: Criticité | G4: Justification Danone | J4: Impact
A5: Prix du lait cru (collecte laitière) | B5: 4 | C5: 5 | D5: =B5*C5 -> 20 | E5: =RANK(D5,$D$5:$D$22) -> 1 | F5: =IF(D5>=15,"Critique",IF(D5>=10,"Élevé",IF(D5>=5,"Modéré","Faible"))) -> Critique | G5: Prix du lait = 1er poste d'achat de l'activité laitière ; volatilité forte et négociations annuelles avec les OP d'éleveurs. | J5: 1 | K5: 2 | L5: 3 | M5: 4 | N5: 5
A6: Prix des matières premières agricoles (sucre, fruits, soja, avoine, amandes) | B6: 4 | C6: 4 | D6: =B6*C6 -> 16 | E6: =RANK(D6,$D$5:$D$22) -> 3 | F6: =IF(D6>=15,"Critique",IF(D6>=10,"Élevé",IF(D6>=5,"Modéré","Faible"))) -> Critique | G6: Sucre, fruits, cacao et végétaux (soja, avoine, amandes pour Alpro) exposés aux aléas climatiques. | H6: Fréquence | I6: 5 | J6: =J$5*$I6 -> 5 | K6: =K$5*$I6 -> 10 | L6: =L$5*$I6 -> 15 | M6: =M$5*$I6 -> 20 | N6: =N$5*$I6 -> 25
A7: Prix de l'énergie / carburants | B7: 4 | C7: 4 | D7: =B7*C7 -> 16 | E7: =RANK(D7,$D$5:$D$22) -> 3 | F7: =IF(D7>=15,"Critique",IF(D7>=10,"Élevé",IF(D7>=5,"Modéré","Faible"))) -> Critique | G7: Sites industriels énergivores (UHT, froid, embouteillage) ; transport de produits frais et d'eaux pondéreuses. | I7: 4 | J7: =J$5*$I7 -> 4 | K7: =K$5*$I7 -> 8 | L7: =L$5*$I7 -> 12 | M7: =M$5*$I7 -> 16 | N7: =N$5*$I7 -> 20
A8: Prix et disponibilité des emballages (PET, rPET, carton) | B8: 3 | C8: 4 | D8: =B8*C8 -> 12 | E8: =RANK(D8,$D$5:$D$22) -> 9 | F8: =IF(D8>=15,"Critique",IF(D8>=10,"Élevé",IF(D8>=5,"Modéré","Faible"))) -> Élevé | G8: Bouteilles d'eau en PET / rPET : tension sur le rPET de qualité alimentaire liée aux objectifs de recyclé. | I8: 3 | J8: =J$5*$I8 -> 3 | K8: =K$5*$I8 -> 6 | L8: =L$5*$I8 -> 9 | M8: =M$5*$I8 -> 12 | N8: =N$5*$I8 -> 15
A9: Réchauffement climatique / sécheresses | B9: 5 | C9: 4 | D9: =B9*C9 -> 20 | E9: =RANK(D9,$D$5:$D$22) -> 1 | F9: =IF(D9>=15,"Critique",IF(D9>=10,"Élevé",IF(D9>=5,"Modéré","Faible"))) -> Critique | G9: Sécheresses = baisse de la pousse de l'herbe, de la collecte et des rendements agricoles. | I9: 2 | J9: =J$5*$I9 -> 2 | K9: =K$5*$I9 -> 4 | L9: =L$5*$I9 -> 6 | M9: =M$5*$I9 -> 8 | N9: =N$5*$I9 -> 10
A10: Ressource en eau (sources minérales, nappes) | B10: 3 | C10: 5 | D10: =B10*C10 -> 15 | E10: =RANK(D10,$D$5:$D$22) -> 8 | F10: =IF(D10>=15,"Critique",IF(D10>=10,"Élevé",IF(D10>=5,"Modéré","Faible"))) -> Critique | G10: Évolution des débits des sources ; restrictions d'usage et contestation locale des prélèvements (eaux minérales). | I10: 1 | J10: =J$5*$I10 -> 1 | K10: =K$5*$I10 -> 2 | L10: =L$5*$I10 -> 3 | M10: =M$5*$I10 -> 4 | N10: =N$5*$I10 -> 5
A11: Réglementations sanitaires / nutritionnelles | B11: 2 | C11: 5 | D11: =B11*C11 -> 10 | E11: =RANK(D11,$D$5:$D$22) -> 15 | F11: =IF(D11>=15,"Critique",IF(D11>=10,"Élevé",IF(D11>=5,"Modéré","Faible"))) -> Élevé | G11: Nutrition infantile et médicale : tolérance zéro, risque de rappel produit majeur (fréquence faible, impact maximal).
A12: Réglementations environnementales (emballages, méthane, CSRD) | B12: 4 | C12: 3 | D12: =B12*C12 -> 12 | E12: =RANK(D12,$D$5:$D$22) -> 9 | F12: =IF(D12>=15,"Critique",IF(D12>=10,"Élevé",IF(D12>=5,"Modéré","Faible"))) -> Élevé | G12: Directive PPWR, loi AGEC, réduction du méthane, CSRD : surcoûts et adaptations des emballages et de l'amont.
A13: Fiabilité des fournisseurs / renouvellement des éleveurs | B13: 4 | C13: 4 | D13: =B13*C13 -> 16 | E13: =RANK(D13,$D$5:$D$22) -> 3 | F13: =IF(D13>=15,"Critique",IF(D13>=10,"Élevé",IF(D13>=5,"Modéré","Faible"))) -> Critique | G13: Vieillissement et non-renouvellement des éleveurs, déconversion laitière dans certains bassins. | I13: Nombre de risques Danone par case
A14: Stabilité géopolitique des zones de production | B14: 3 | C14: 4 | D14: =B14*C14 -> 12 | E14: =RANK(D14,$D$5:$D$22) -> 9 | F14: =IF(D14>=15,"Critique",IF(D14>=10,"Élevé",IF(D14>=5,"Modéré","Faible"))) -> Élevé | G14: Exposition aux pays émergents (Afrique, Asie, Amérique latine) ; sortie de Russie récente. | J14: Impact
A15: Fiabilité logistique / routes maritimes | B15: 3 | C15: 3 | D15: =B15*C15 -> 9 | E15: =RANK(D15,$D$5:$D$22) -> 16 | F15: =IF(D15>=15,"Critique",IF(D15>=10,"Élevé",IF(D15>=5,"Modéré","Faible"))) -> Modéré | G15: Mer Rouge / Suez, congestion portuaire ; produits frais intolérants aux retards. | J15: 1 | K15: 2 | L15: 3 | M15: 4 | N15: 5
A16: Tarifs douaniers / protectionnisme | B16: 4 | C16: 3 | D16: =B16*C16 -> 12 | E16: =RANK(D16,$D$5:$D$22) -> 9 | F16: =IF(D16>=15,"Critique",IF(D16>=10,"Élevé",IF(D16>=5,"Modéré","Faible"))) -> Élevé | G16: Droits de douane US / Chine sur les produits laitiers et ingrédients, mesures de rétorsion. | H16: Fréquence | I16: 5 | J16: =IF(COUNTIFS($B$5:$B$22,$I16,$C$5:$C$22,J$15)=0,"",COUNTIFS($B$5:$B$22,$I16,$C$5:$C$22,J$15)) | K16: =IF(COUNTIFS($B$5:$B$22,$I16,$C$5:$C$22,K$15)=0,"",COUNTIFS($B$5:$B$22,$I16,$C$5:$C$22,K$15)) | L16: =IF(COUNTIFS($B$5:$B$22,$I16,$C$5:$C$22,L$15)=0,"",COUNTIFS($B$5:$B$22,$I16,$C$5:$C$22,L$15)) | M16: =IF(COUNTIFS($B$5:$B$22,$I16,$C$5:$C$22,M$15)=0,"",COUNTIFS($B$5:$B$22,$I16,$C$5:$C$22,M$15)) -> 1 | N16: =IF(COUNTIFS($B$5:$B$22,$I16,$C$5:$C$22,N$15)=0,"",COUNTIFS($B$5:$B$22,$I16,$C$5:$C$22,N$15))
A17: Sanctions internationales / compliance | B17: 2 | C17: 4 | D17: =B17*C17 -> 8 | E17: =RANK(D17,$D$5:$D$22) -> 18 | F17: =IF(D17>=15,"Critique",IF(D17>=10,"Élevé",IF(D17>=5,"Modéré","Faible"))) -> Modéré | G17: Contrôles export, sanctions, devoir de vigilance, déforestation (règlement RDUE sur soja / cacao). | I17: 4 | J17: =IF(COUNTIFS($B$5:$B$22,$I17,$C$5:$C$22,J$15)=0,"",COUNTIFS($B$5:$B$22,$I17,$C$5:$C$22,J$15)) | K17: =IF(COUNTIFS($B$5:$B$22,$I17,$C$5:$C$22,K$15)=0,"",COUNTIFS($B$5:$B$22,$I17,$C$5:$C$22,K$15)) | L17: =IF(COUNTIFS($B$5:$B$22,$I17,$C$5:$C$22,L$15)=0,"",COUNTIFS($B$5:$B$22,$I17,$C$5:$C$22,L$15)) -> 3 | M17: =IF(COUNTIFS($B$5:$B$22,$I17,$C$5:$C$22,M$15)=0,"",COUNTIFS($B$5:$B$22,$I17,$C$5:$C$22,M$15)) -> 5 | N17: =IF(COUNTIFS($B$5:$B$22,$I17,$C$5:$C$22,N$15)=0,"",COUNTIFS($B$5:$B$22,$I17,$C$5:$C$22,N$15)) -> 1
A18: Épizooties (FCO, fièvre aphteuse, grippe aviaire) | B18: 3 | C18: 4 | D18: =B18*C18 -> 12 | E18: =RANK(D18,$D$5:$D$22) -> 9 | F18: =IF(D18>=15,"Critique",IF(D18>=10,"Élevé",IF(D18>=5,"Modéré","Faible"))) -> Élevé | G18: FCO, fièvre aphteuse, grippe aviaire : abattages, restrictions de mouvements, baisse de collecte. | I18: 3 | J18: =IF(COUNTIFS($B$5:$B$22,$I18,$C$5:$C$22,J$15)=0,"",COUNTIFS($B$5:$B$22,$I18,$C$5:$C$22,J$15)) | K18: =IF(COUNTIFS($B$5:$B$22,$I18,$C$5:$C$22,K$15)=0,"",COUNTIFS($B$5:$B$22,$I18,$C$5:$C$22,K$15)) | L18: =IF(COUNTIFS($B$5:$B$22,$I18,$C$5:$C$22,L$15)=0,"",COUNTIFS($B$5:$B$22,$I18,$C$5:$C$22,L$15)) -> 2 | M18: =IF(COUNTIFS($B$5:$B$22,$I18,$C$5:$C$22,M$15)=0,"",COUNTIFS($B$5:$B$22,$I18,$C$5:$C$22,M$15)) -> 3 | N18: =IF(COUNTIFS($B$5:$B$22,$I18,$C$5:$C$22,N$15)=0,"",COUNTIFS($B$5:$B$22,$I18,$C$5:$C$22,N$15)) -> 1
A19: Tendances de consommation / opinion (végétal, santé, boycotts) | B19: 4 | C19: 3 | D19: =B19*C19 -> 12 | E19: =RANK(D19,$D$5:$D$22) -> 9 | F19: =IF(D19>=15,"Critique",IF(D19>=10,"Élevé",IF(D19>=5,"Modéré","Faible"))) -> Élevé | G19: Montée du végétal, de la santé / protéines, risques de boycott et d'image (plastique, eau). | I19: 2 | J19: =IF(COUNTIFS($B$5:$B$22,$I19,$C$5:$C$22,J$15)=0,"",COUNTIFS($B$5:$B$22,$I19,$C$5:$C$22,J$15)) | K19: =IF(COUNTIFS($B$5:$B$22,$I19,$C$5:$C$22,K$15)=0,"",COUNTIFS($B$5:$B$22,$I19,$C$5:$C$22,K$15)) | L19: =IF(COUNTIFS($B$5:$B$22,$I19,$C$5:$C$22,L$15)=0,"",COUNTIFS($B$5:$B$22,$I19,$C$5:$C$22,L$15)) | M19: =IF(COUNTIFS($B$5:$B$22,$I19,$C$5:$C$22,M$15)=0,"",COUNTIFS($B$5:$B$22,$I19,$C$5:$C$22,M$15)) -> 1 | N19: =IF(COUNTIFS($B$5:$B$22,$I19,$C$5:$C$22,N$15)=0,"",COUNTIFS($B$5:$B$22,$I19,$C$5:$C$22,N$15)) -> 1
A20: Pression de la distribution & concurrence (MDD, Egalim) | B20: 4 | C20: 4 | D20: =B20*C20 -> 16 | E20: =RANK(D20,$D$5:$D$22) -> 3 | F20: =IF(D20>=15,"Critique",IF(D20>=10,"Élevé",IF(D20>=5,"Modéré","Faible"))) -> Critique | G20: Négociations commerciales tendues avec la GMS, montée des MDD, cadre Egalim. | I20: 1 | J20: =IF(COUNTIFS($B$5:$B$22,$I20,$C$5:$C$22,J$15)=0,"",COUNTIFS($B$5:$B$22,$I20,$C$5:$C$22,J$15)) | K20: =IF(COUNTIFS($B$5:$B$22,$I20,$C$5:$C$22,K$15)=0,"",COUNTIFS($B$5:$B$22,$I20,$C$5:$C$22,K$15)) | L20: =IF(COUNTIFS($B$5:$B$22,$I20,$C$5:$C$22,L$15)=0,"",COUNTIFS($B$5:$B$22,$I20,$C$5:$C$22,L$15)) | M20: =IF(COUNTIFS($B$5:$B$22,$I20,$C$5:$C$22,M$15)=0,"",COUNTIFS($B$5:$B$22,$I20,$C$5:$C$22,M$15)) | N20: =IF(COUNTIFS($B$5:$B$22,$I20,$C$5:$C$22,N$15)=0,"",COUNTIFS($B$5:$B$22,$I20,$C$5:$C$22,N$15))
A21: Climat social (agricole et industriel) | B21: 3 | C21: 3 | D21: =B21*C21 -> 9 | E21: =RANK(D21,$D$5:$D$22) -> 16 | F21: =IF(D21>=15,"Critique",IF(D21>=10,"Élevé",IF(D21>=5,"Modéré","Faible"))) -> Modéré | G21: Mobilisations agricoles, grèves industrielles ou logistiques.
A22: Cours mondiaux / spéculation (poudre de lait, beurre, sucre) | B22: 4 | C22: 4 | D22: =B22*C22 -> 16 | E22: =RANK(D22,$D$5:$D$22) -> 3 | F22: =IF(D22>=15,"Critique",IF(D22>=10,"Élevé",IF(D22>=5,"Modéré","Faible"))) -> Critique | G22: Cours GDT / Euronext (poudre, beurre, sucre) très volatils, impact direct sur les prix d'achat.
A23: Échelle de notation | B23: 1 à 5 | C23: 1 à 5
A24: Criticité : ≥15 Critique · 10-14 Élevé · 5-9 Modéré · <5 Faible

Sheet Matrice prospective
A1: Matrice prospective – scénarios à 5 ans (horizon 2031)
B3: Hypothèses
A4: Variables clés | B4: Continuum | C4: Renforcement | D4: Explosion | E4: Affaiblissement | F4: Effondrement
A5: Prix du lait cru | B5: Volatilité avec tendance haussière modérée (+2 %/an) ; négociations annuelles tendues avec les OP. | C5: Décapitalisation laitière en Europe : +5 %/an, primes de qualité et contrats pluriannuels généralisés. | D5: Pénurie de lait dans plusieurs bassins : +12 %/an, pics ponctuels à +25 %, rationnement de la collecte. | E5: Stabilisation (+0,5 %/an) grâce aux gains de productivité et au retour de la production en Océanie. | F5: Surproduction mondiale, chute des prix (-5 %/an) et crise des revenus des éleveurs.
A6: Prix des matières premières agricoles | B6: Hausse tendancielle +4 %/an (sucre, fruits, cacao), forte variabilité. | C6: +7 %/an : récoltes dégradées, concurrence des usages (biocarburants) sur le sucre et les végétaux. | D6: +15 %/an, ruptures de disponibilité sur le cacao, certains fruits et l'amande (Californie). | E6: +1 %/an, détente des marchés après de bonnes récoltes successives. | F6: Baisse générale des cours (-3 %/an), surcapacités mondiales.
A7: Prix de l'énergie / carburants | B7: Instabilité avec pics, tendance +3 %/an ; taxe carbone croissante. | C7: +5 %/an, renchérissement du gaz et du quota CO2 (ETS2 transport). | D7: Choc énergétique : +10 %/an, arrêts temporaires de lignes énergivores. | E7: +1 %/an, PPA renouvelables et électrification des sites amortissent la hausse. | F7: Baisse durable des prix (-1 %/an), abondance de GNL et d'électricité décarbonée.
A8: Emballages (PET / rPET) | B8: rPET rare et plus cher que le vierge (+20 à 30 %), approvisionnement tendu. | C8: Obligations PPWR : quotas de recyclé et de réemploi, surcoût emballage +6 %/an. | D8: Interdiction progressive des plastiques à usage unique sur certains formats : rupture du modèle bouteille PET. | E8: Massification du recyclage, rPET au prix du vierge, nouvelles capacités de recyclage chimique. | F8: Retour en arrière réglementaire, plastique vierge bon marché, pression sur l'image.
A9: Réchauffement climatique / eau | B9: +1,5 °C, sécheresses récurrentes, stress hydrique estival, baisse de collecte en été. | C9: +1,7 °C, sécheresses annuelles, restrictions de prélèvements pour les sites d'embouteillage. | D9: +2 °C, débit des sources en baisse durable, conflits d'usage ouverts, fermeture de certains captages. | E9: +1,3 °C, épisodes extrêmes plus rares, recharge correcte des nappes. | F9: Retour de l'humidité et adoucissement, conditions de pousse de l'herbe favorables.
A10: Réglementations environnementales | B10: Renforcement modéré et différencié selon les zones (UE stricte, reste du monde souple). | C10: Accélération : taxation du méthane agricole, reporting CSRD complet, RDUE strictement appliqué. | D10: Encadrement strict de toute la chaîne (quotas carbone agricoles, eau, emballages). | E10: Assouplissement des normes hors GES (simplification « omnibus » UE). | F10: Abandon quasi total des contraintes environnementales, au profit de la compétitivité.
A11: Fiabilité des fournisseurs / éleveurs | B11: Érosion lente du nombre d'éleveurs (-2 à 3 %/an), vieillissement, concentration des exploitations. | C11: -5 %/an : déconversion laitière, le sourcing doit se redéployer vers d'autres bassins. | D11: Crise grave du monde agricole, disparition de bassins laitiers entiers, volumes insuffisants. | E11: Stabilisation grâce aux contrats de long terme et à l'installation de jeunes éleveurs. | F11: Rebond des installations et des cheptels, offre abondante.
A12: Stabilité géopolitique / logistique | B12: Instabilité diffuse, résilience globale ; incidents ponctuels (Mer Rouge). | C12: Recrudescence des conflits, routes maritimes déviées, fret +20 %, assurances en hausse. | D12: Fermeture durable d'un détroit majeur, ruptures d'approvisionnement en ingrédients importés. | E12: Apaisement relatif, normalisation des routes et des taux de fret. | F12: Chaînes fluides et peu coûteuses, effondrement des risques logistiques.
A13: Tarifs douaniers / sanctions | B13: Barrières ciblées qui se multiplient, avec reculs et forte incertitude. | C13: Croissance continue des barrières hors accords de libre-échange, rétorsions sur les produits laitiers. | D13: Guerre commerciale ouverte (US / Chine / UE), marchés export fermés, sanctions élargies. | E13: Retour à des accords bilatéraux, baisse ciblée des droits. | F13: Accord global à l'OMC, harmonisation normative et levée des sanctions.
A14: Épizooties | B14: Épisodes réguliers (FCO, grippe aviaire), pertes de collecte localisées de 1 à 2 %. | C14: Épizooties annuelles plus étendues avec la remontée des vecteurs vers le nord, -4 % de collecte. | D14: Fièvre aphteuse généralisée en Europe : abattages massifs, embargos, -15 % de collecte. | E14: Vaccination généralisée, épisodes rares et maîtrisés. | F14: Quasi-disparition des épizooties majeures.
A15: Tendances de consommation | B15: Croissance lente du végétal et des produits santé / protéinés, stagnation des yaourts classiques en OCDE. | C15: Forte accélération santé / protéines / microbiote, croissance forte des pays émergents. | D15: Défiance massive (plastique, eau minérale, ultra-transformés), boycotts répétés des marques. | E15: Retour au prix : arbitrages vers les MDD, baisse des volumes de marque. | F15: Effondrement des catégories premium, forte déconsommation.
A16: Cours mondiaux / spéculation | B16: Très aléatoires, fortes hausses occasionnelles (poudre, beurre, sucre). | C16: Volatilité accrue, financiarisation des marchés agricoles, amplitude ±30 %. | D16: Bulle spéculative suivie d'un krach, impossibilité de couvrir les achats. | E16: Volatilité réduite, encadrement des positions spéculatives. | F16: Prix bas et stables, faible intérêt des fonds pour les marchés agricoles.

Sheet Scénarios
A1: Scénarios narratifs Danone 2031
A2: Construits en partant majoritairement des hypothèses « renforcement » et « affaiblissement », avec un chemin cohérent entre variables.
A4: Scénario | B4: Chemin d'hypothèses | C4: Texte narratif
A5: Scénario 1 – « Tensions durables » (chemin : renforcement) | B5: Lait : renforcement · MP agricoles : renforcement · Énergie : continuum · Emballages : renforcement · Climat/eau : renforcement · Régl. env. : renforcement · Éleveurs : renforcement · Géopolitique : renforcement · Tarifs : renforcement · Épizooties : renforcement · Conso : continuum · Cours : renforcement | C5: À l'horizon 2031, le réchauffement (+1,7 °C) installe des sécheresses annuelles qui réduisent la pousse de l'herbe et accélèrent la déconversion laitière en Europe. Danone doit sécuriser son lait dans un marché en contraction : les prix progressent d'environ 5 %/an et les contrats pluriannuels deviennent la norme. Les sites d'Evian et de Volvic sont soumis à des restrictions estivales de prélèvement. Parallèlement, le règlement PPWR impose des taux de recyclé que le marché du rPET ne peut pas fournir à bas coût, et les épizooties plus fréquentes perturbent régulièrement la collecte. Les routes maritimes restent instables et les droits de douane se multiplient, ce qui renchérit les ingrédients importés (cacao, amandes, protéines). La marge brute est sous pression constante et la fonction achats devient un levier de résilience plus qu'un levier de coût.
A6: Scénario 2 – « Transition maîtrisée » (chemin : affaiblissement) | B6: Lait : affaiblissement · MP : affaiblissement · Énergie : affaiblissement · Emballages : affaiblissement · Climat/eau : continuum · Régl. env. : continuum · Éleveurs : affaiblissement · Géopolitique : affaiblissement · Tarifs : affaiblissement · Épizooties : affaiblissement · Conso : renforcement · Cours : affaiblissement | C6: Les tensions des années 2020 s'apaisent progressivement. La vaccination limite l'impact des épizooties, le nombre d'éleveurs se stabilise grâce aux contrats de long terme et aux programmes d'agriculture régénératrice, et le prix du lait évolue peu. La massification du recyclage aligne le rPET sur le prix du plastique vierge. Les PPA renouvelables stabilisent la facture énergétique. Le climat reste contraignant (+1,5 °C), mais les investissements dans la gestion de l'eau sécurisent les sources. La demande santé / protéines / végétal accélère, notamment dans les pays émergents : l'enjeu achats bascule vers la sécurisation de nouveaux ingrédients (protéines végétales, ferments, fibres) et l'innovation fournisseurs.
A7: Scénario 3 – « Continuum volatil » (chemin : continuum) | B7: Toutes variables : continuum, avec des chocs ponctuels (pic énergétique, épizootie, incident en Mer Rouge) | C7: Aucune rupture majeure, mais une succession de chocs courts et imprévisibles. Les prix du lait et des matières premières progressent de 2 à 4 %/an avec de fortes variations ; la logistique reste perturbée sans se rompre ; les réglementations environnementales se renforcent en Europe et restent souples ailleurs, ce qui crée des asymétries de concurrence. La distribution maintient une forte pression sur les prix (MDD, Egalim). Danone doit piloter en permanence l'agilité de ses approvisionnements (double sourcing, stocks de sécurité ciblés, couverture partielle des cours).

Sheet Recommandations
A1: Recommandations par rapport aux scénarios réalisés
A2: Choix d'une stratégie achats par famille de risque
A4: Famille de risque | B4: Criticité | C4: Stratégie retenue | D4: Actions achats | E4: Scénarios couverts
A5: Lait cru / éleveurs | B5: Critique | C5: Sécurisation & partenariat amont | D5: Contrats pluriannuels avec prix indexés sur les coûts de production (Egalim), primes à l'agriculture régénératrice, aide à l'installation des jeunes éleveurs, diversification géographique des bassins de collecte. | E5: 1, 3
A6: Cours mondiaux / MP agricoles | B6: Élevé | C6: Couverture & diversification | D6: Couverture financière partielle (futures poudre de lait / sucre), multi-sourcing des fruits et végétaux, substitution de recettes (réduction du sucre), stocks stratégiques sur le cacao et les amandes. | E6: 1, 3
A7: Climat / ressource en eau | B7: Critique | C7: Résilience & préservation de la ressource | D7: Protection des impluviums (partenariats avec les agriculteurs locaux), réduction des prélèvements par litre produit, plans de continuité en cas de restriction, dialogue avec les parties prenantes locales. | E7: 1
A8: Emballages PET / rPET | B8: Élevé | C8: Intégration amont & innovation | D8: Contrats long terme ou prises de participation dans des recycleurs, co-développement de recyclage chimique, développement du réemploi et des formats alternatifs (verre, canette, fontaines). | E8: 1, 2
A9: Énergie | B9: Élevé | C9: Réduction de la dépendance | D9: PPA renouvelables sur 10-15 ans, électrification et efficacité énergétique des sites, achats d'énergie lissés sur plusieurs années. | E9: 1, 3
A10: Géopolitique / logistique / tarifs | B10: Élevé | C10: Régionalisation | D10: Production au plus près des marchés (« local for local »), routes alternatives, stocks tampon sur les ingrédients importés, veille tarifaire et optimisation de l'origine douanière. | E10: 1, 3
A11: Épizooties / sanitaire | B11: Élevé | C11: Prévention & redondance | D11: Plans de biosécurité avec les éleveurs, soutien à la vaccination, double qualification des fournisseurs d'ingrédients infantiles, traçabilité renforcée. | E11: 1, 3
A12: Consommation / distribution | B12: Élevé | C12: Agilité du portefeuille | D12: Sourcing de nouvelles protéines (végétal, fermentation), achats flexibles pour suivre l'arbitrage marque / MDD, transparence RSE pour limiter les risques d'image. | E12: 2, 3
A14: Synthèse stratégique
A15: Face à des risques majoritairement structurels (climat, éleveurs, eau, emballages), Danone a intérêt à privilégier une stratégie de SÉCURISATION et de PARTENARIAT de long terme avec l'amont agricole plutôt qu'une logique purement transactionnelle. Elle doit être complétée par une couverture financière sur les matières cotées et par une régionalisation des chaînes d'approvisionnement pour limiter l'exposition géopolitique. La veille sur les variables motrices (climat, géopolitique, énergie, réglementations) doit alimenter une révision annuelle de la matrice de risques.
